{
    "id": "psi_field_interaction_models",
    "name": "Psi Field Interaction Models",
    "description": "A structured exploration of how psi fields interact with consciousness, physical systems, and energy fields.",
    "focus": [
        "Psi Field and Consciousness",
        "Psi Field and Electromagnetic Fields",
        "Psi Field and Quantum Mechanics",
        "Psi Field in Biological Systems"
    ],
    "cards": [
        {
            "id": "psi_consciousness",
            "title": "Psi Field and Consciousness",
            "description": "Examining the direct interaction between psi energy and human consciousness.",
            "bulletpoints": [
                "Psi fields are influenced by thought, intention, and focus, creating measurable changes in psi energy levels.",
                "Psi energy follows non-local interaction principles, meaning consciousness can affect distant systems.",
                "Equations modeling consciousness interaction: \\[ \\Psi_c = \\sum_{i} w_i \\cdot e^{i \\theta_i} \\], where \\( \\theta \\) represents mental state coherence."
            ],
            "summaryText": "Treat coherent thought as the phase control knob that steers psi amplitudes across space.",
            "duration": 12,
            "difficulty": "Intermediate"
        },
        {
            "id": "psi_electromagnetic",
            "title": "Psi Field and Electromagnetic Fields",
            "description": "How psi energy interacts with and modifies electromagnetic fields.",
            "bulletpoints": [
                "Psi fields can modulate EM waves, influencing radio signals, light, and brainwave activity.",
                "Psi-energy coupled Maxwell equations: \\[ \\nabla \\times \\Psi + \\frac{\\partial E}{\\partial t} = 0 \\] shows psi-induced EM fluctuations.",
                "Research suggests psi fields can resonate with Schumann frequencies, affecting consciousness."
            ],
            "summaryText": "Remember that psi-EM coupling shows up as subtle resonances and phase drifts riding classical signals.",
            "duration": 14,
            "difficulty": "Advanced"
        },
        {
            "id": "psi_quantum_mechanics",
            "title": "Psi Field and Quantum Mechanics",
            "description": "Exploring the relationship between psi fields and quantum non-locality.",
            "bulletpoints": [
                "Psi fields exhibit non-local entanglement effects, similar to quantum mechanics.",
                "Psi-based quantum state function: \\[ \\Psi_q = \\sum_k e^{i S_k / \\hbar} \\], where \\( S_k \\) is psi-driven action.",
                "Psi-enhanced quantum tunneling suggests faster-than-light energy transfer is possible."
            ],
            "summaryText": "Link psi behavior to entangled phase sums that bias quantum outcomes toward intention.",
            "duration": 16,
            "difficulty": "Expert"
        },
        {
            "id": "psi_interference_patterns",
            "title": "Psi Field Interference Patterns",
            "description": "Understanding wave-like interference in psi energy fields.",
            "bulletpoints": [
                "Psi fields can experience constructive and destructive interference, forming complex wave structures.",
                "Equation for psi wave interference: \\[ \\Psi_{total} = \\Psi_1 + \\Psi_2 e^{i \\phi} \\], where \\( \\phi \\) is the phase shift.",
                "Applications in psionic communication, remote viewing, and thought projection."
            ],
            "summaryText": "Visualize overlapping psi waves summing or canceling to tune communication clarity.",
            "duration": 14,
            "difficulty": "Advanced"
        },
        {
            "id": "psi_biological_systems",
            "title": "Psi Field in Biological Systems",
            "description": "Examining the effects of psi energy on living organisms.",
            "bulletpoints": [
                "Psi fields interact with bioelectric signals, affecting neural activity and cellular function.",
                "Psi-energy biological coupling equation: \\[ \\frac{dV}{dt} = I_{\\Psi} - I_{bio} \\], where \\( I_{\\Psi} \\) is psi energy input.",
                "Experiments suggest psi fields influence DNA expression, neuroplasticity, and healing rates."
            ],
            "summaryText": "Think of psi input as a supplemental current nudging neural and cellular dynamics toward balance.",
            "duration": 16,
            "difficulty": "Expert"
        },
        {
            "id": "psi_intention_projection",
            "title": "Psi Field and Intention Projection",
            "description": "How focused intention influences psi field strength and coherence.",
            "bulletpoints": [
                "Psi energy responds to mental focus, visualization, and emotional states.",
                "Psi field coherence function: \\[ \\Psi_{int} = \\sum_i w_i \\cdot \\rho_i e^{i \\theta_i} \\], where \\( \\rho \\) is emotional resonance.",
                "Applications in manifestation techniques, telekinesis, and remote influence."
            ],
            "summaryText": "Use aligned emotion and focus to tighten psi phase coherence and raise output.",
            "duration": 12,
            "difficulty": "Intermediate"
        },
        {
            "id": "psi_psionics",
            "title": "Psi Field in Meditation & Psionics",
            "description": "Psi energy control through advanced mental training.",
            "bulletpoints": [
                "Meditation techniques increase psi field stability and energy flow.",
                "Training exercises involve visualizing energy movement, resonant breathing, and harmonic entrainment.",
                "Psi amplification equation: \\[ \\Psi_{amp} = \\int_0^T \\Psi_c dt \\], representing psi energy accumulation over time."
            ],
            "summaryText": "Treat meditation drills as integrators that accumulate coherent psi charge over time.",
            "duration": 12,
            "difficulty": "Intermediate"
        },
        {
            "id": "psi_energy_conservation",
            "title": "Psi Energy Conservation Models",
            "description": "Mathematical principles governing the conservation of psi energy.",
            "bulletpoints": [
                "Psi energy follows a conservation law, similar to classical physics.",
                "Psi continuity equation: \\[ \\frac{d\\Psi}{dt} + \\nabla \\cdot (\\Psi v) = 0 \\], ensuring energy balance.",
                "Applications in psi shielding, energy reinforcement, and sustainable psionics."
            ],
            "summaryText": "Model psi work with continuity math so you budget inflows, outflows, and storage deliberately.",
            "duration": 16,
            "difficulty": "Advanced"
        }
    ]
}